sense_data2/__init__.py
sense_data2/client.py
sense_data2/dictobj.py
sense_data2/dictobj1.py
sense_data2/dictobj2.py
sense_data2/stock_pb2.py
sense_data2/stock_pb2_grpc.py
sense_data2/test.py
sense_data2-0.0.1.dist-info/DESCRIPTION.rst
sense_data2-0.0.1.dist-info/METADATA
sense_data2-0.0.1.dist-info/RECORD
sense_data2-0.0.1.dist-info/WHEEL
sense_data2-0.0.1.dist-info/metadata.json
sense_data2-0.0.1.dist-info/top_level.txt
